LICENSE
LICENSE.txt
README.md
pyproject.toml
setup.py
martas/__init__.py
martas/acquisition.py
martas/collector.py
martas/martas_init.py
martas/version.py
martas.egg-info/PKG-INFO
martas.egg-info/SOURCES.txt
martas.egg-info/dependency_links.txt
martas.egg-info/requires.txt
martas.egg-info/top_level.txt
martas/app/__init__.py
martas/app/archive.py
martas/app/ardcomm.py
martas/app/backup.py
martas/app/basevalue.py
martas/app/checkdatainfo.py
martas/app/db_truncate.py
martas/app/di.py
martas/app/file_download.py
martas/app/file_upload.py
martas/app/filter.py
martas/app/gamma.py
martas/app/monitor.py
martas/app/obsdaq.py
martas/app/optimizetables.py
martas/app/palmacq.py
martas/app/serialinit.py
martas/app/speedtest.py
martas/app/statemachine.py
martas/app/telegrambot.py
martas/app/testnote.py
martas/app/testserial.py
martas/app/threshold.py
martas/conf/archive.cfg
martas/conf/basevalue.cfg
martas/conf/download-source.cfg
martas/conf/fileuploadjobs.json
martas/conf/filter.cfg
martas/conf/gamma.cfg
martas/conf/mail.cfg
martas/conf/marcos.cfg
martas/conf/martas.cfg
martas/conf/monitor.cfg
martas/conf/obsdaq.cfg
martas/conf/sensors.cfg
martas/conf/telegram.cfg
martas/conf/telegrambot.cfg
martas/conf/threshold.cfg
martas/core/__init__.py
martas/core/acquisitionsupport.py
martas/core/analysis.py
martas/core/app_tester.py
martas/core/definitive.py
martas/core/message.py
martas/core/methods.py
martas/core/websocket_server.py
martas/doc/marcos_viewer.png
martas/doc/martas_concept.png
martas/doc/martas_viewer.png
martas/doc/namingconvention.png
martas/init/bm35init.sh
martas/init/gsm90v6init.sh
martas/init/gsm90v7init.sh
martas/init/lminit.sh
martas/init/obsdaqinit.sh
martas/init/pos1init.sh
martas/init/worklist.json
martas/lib/__init__.py
martas/lib/activearduinoprotocol.py
martas/lib/ad7714protocol.py
martas/lib/arduinoprotocol.py
martas/lib/bm35protocol.py
martas/lib/bme280i2cprotocol.py
martas/lib/cr1000jcprotocol.py
martas/lib/csprotocol.py
martas/lib/disdroprotocol.py
martas/lib/dspprotocol.py
martas/lib/envprotocol.py
martas/lib/fluke289protocol.py
martas/lib/fourplprotocol.py
martas/lib/gicprotocol.py
