Metadata-Version: 2.1
Name: martas
Version: 2.0.0rc3
Summary: MARTAS
Home-page: 
Author: R. Leonhardt, R. Bailey, R. Mandl, V. Haberle
Author-email: roman.leonhardt@geosphere.at
License: LICENSE.txt
License-File: LICENSE
License-File: LICENSE.txt
Requires-Dist: geomagpy>1.1.9
Requires-Dist: numpy>=1.21.0
Requires-Dist: scipy>=1.7.1
Requires-Dist: pexpect
Requires-Dist: paramiko
Requires-Dist: pyserial
Requires-Dist: requests
Requires-Dist: python-crontab
Requires-Dist: twisted
Requires-Dist: plotly
Requires-Dist: dash
Requires-Dist: dash_daq
Requires-Dist: psutil
Requires-Dist: setuptools>=61.0.0
